.coveragerc
.gitignore
.landscape.yml
.travis.yml
LICENSE
MANIFEST.in
README.rst
buildout.cfg
setup.py
travis.cfg
cs/__init__.py
cs.portlet.calendar.egg-info/PKG-INFO
cs.portlet.calendar.egg-info/SOURCES.txt
cs.portlet.calendar.egg-info/dependency_links.txt
cs.portlet.calendar.egg-info/entry_points.txt
cs.portlet.calendar.egg-info/namespace_packages.txt
cs.portlet.calendar.egg-info/not-zip-safe
cs.portlet.calendar.egg-info/requires.txt
cs.portlet.calendar.egg-info/top_level.txt
cs/portlet/__init__.py
cs/portlet/calendar/__init__.py
cs/portlet/calendar/configure.zcml
cs/portlet/calendar/events.py
cs/portlet/calendar/portlet.pt
cs/portlet/calendar/portlet.py
cs/portlet/calendar/rebuild_i18n.sh
cs/portlet/calendar/testing.py
cs/portlet/calendar/version.txt
cs/portlet/calendar/locales/cs.portlet.calendar-manual.pot
cs/portlet/calendar/locales/cs.portlet.calendar.pot
cs/portlet/calendar/locales/plone.pot
cs/portlet/calendar/locales/en/LC_MESSAGES/cs.portlet.calendar.po
cs/portlet/calendar/locales/en/LC_MESSAGES/plone.po
cs/portlet/calendar/locales/es/LC_MESSAGES/cs.portlet.calendar.po
cs/portlet/calendar/locales/es/LC_MESSAGES/plone.po
cs/portlet/calendar/locales/eu/LC_MESSAGES/cs.portlet.calendar.po
cs/portlet/calendar/locales/eu/LC_MESSAGES/plone.po
cs/portlet/calendar/profiles/default/metadata.xml
cs/portlet/calendar/profiles/default/portlets.xml
cs/portlet/calendar/resources/CHANGELOG.txt
cs/portlet/calendar/resources/CONTRIBUTING.txt
cs/portlet/calendar/resources/LICENSE.txt
cs/portlet/calendar/resources/fullcalendar.css
cs/portlet/calendar/resources/fullcalendar.js
cs/portlet/calendar/resources/fullcalendar.min.css
cs/portlet/calendar/resources/fullcalendar.min.js
cs/portlet/calendar/resources/fullcalendar.print.css
cs/portlet/calendar/resources/fullcalendar.print.min.css
cs/portlet/calendar/resources/gcal.js
cs/portlet/calendar/resources/gcal.min.js
cs/portlet/calendar/resources/locale-all.js
cs/portlet/calendar/resources/demos/agenda-views.html
cs/portlet/calendar/resources/demos/background-events.html
cs/portlet/calendar/resources/demos/basic-views.html
cs/portlet/calendar/resources/demos/default.html
cs/portlet/calendar/resources/demos/external-dragging.html
cs/portlet/calendar/resources/demos/gcal.html
cs/portlet/calendar/resources/demos/json.html
cs/portlet/calendar/resources/demos/list-views.html
