Metadata-Version: 1.1
Name: cs.portlet.calendar
Version: 1.0
Summary: Calendar portlet using fullcalendar.io
Home-page: https://github.com/codesyntax/cs.portlet.calendar
Author: Mikel Larreategi
Author-email: mlarreategi@codesyntax.com
License: GPLv2
Keywords: plone portlet calendar fullcalendar
Platform: UNKNOWN
Classifier: Framework :: Plone :: 5.0
Classifier: Framework :: Plone :: 5.1
Classifier: Framework :: Plone
Classifier: Programming Language :: Python
